MANIFEST.in
README.md
dependencies.txt
pyproject.toml
setup.cfg
setup.py
tox.ini
docker/Dockerfile
docs/Makefile
docs/conf.py
docs/index.rst
docs/installation.rst
docs/make.bat
docs/modules.rst
docs/usage.rst
listener/__init__.py
listener/daemon.py
listener/dbusservice.py
listener/defaults.py
listener/dockersetup.py
listener/eventreceiver.py
listener/eventserver.py
listener/ibusengine.py
listener/interpreter.py
listener/pipeaudio.py
listener/uinputdriver.py
listener.egg-info/PKG-INFO
listener.egg-info/SOURCES.txt
listener.egg-info/dependency_links.txt
listener.egg-info/entry_points.txt
listener.egg-info/not-zip-safe
listener.egg-info/top_level.txt
listener/static/microphone.svg
listener/static/panel-icon-error.svg
listener/static/panel-icon-paused.svg
listener/static/panel-icon-recording.svg
listener/static/panel-icon-stopped.svg
scripts/ffmpeg-audio.sh
scripts/ffmpeg-sample.sh
scripts/pacat-audio.sh
tests/__init__.py
tests/test_interpreter.py