Metadata-Version: 2.1
Name: listener
Version: 2.0.0a1
Summary: DeepSpeech as a (Docker) Service for IBus
Home-page: https://github.com/mcfletch/listener
Author: Mike C. Fletcher
Author-email: mcfletch@vrplumber.com
License: LGPLv2
Keywords: DeepSpeech Speech Recognition Docker IBus
Platform: UNKNOWN
Classifier: Development Status :: 2 - Pre-Alpha
Classifier: License :: OSI Approved :: GNU Lesser General Public License v2 (LGPLv2)
Classifier: Natural Language :: English
Classifier: Programming Language :: Python :: 3.6
Classifier: Programming Language :: Python :: 3.7
Classifier: Programming Language :: Python :: 3.8
Requires-Python: >=3.6
